<annotation>
	<folder>JPEGImages</folder>
	<filename>000162.jpg</filename>
	<path>JPEGImages</path>
	<size>
		<width>451</width>
		<height>312</height>
		<depth>3</depth>
	</size>
	<object>
		<name>ship</name>
		<pose>Unspecified</pose>
		<truncated>0</truncated>
		<difficult>0</difficult>
		<bndbox>
			<xmin>157</xmin>
			<ymin>53</ymin>
			<xmax>167</xmax>
			<ymax>79</ymax>
		</bndbox>
	</object>
	<object>
		<name>ship</name>
		<pose>Unspecified</pose>
		<truncated>0</truncated>
		<difficult>0</difficult>
		<bndbox>
			<xmin>47</xmin>
			<ymin>154</ymin>
			<xmax>65</xmax>
			<ymax>204</ymax>
		</bndbox>
	</object>
	<object>
		<name>ship</name>
		<pose>Unspecified</pose>
		<truncated>0</truncated>
		<difficult>0</difficult>
		<bndbox>
			<xmin>277</xmin>
			<ymin>204</ymin>
			<xmax>295</xmax>
			<ymax>248</ymax>
		</bndbox>
	</object>
	<object>
		<name>ship</name>
		<pose>Unspecified</pose>
		<truncated>0</truncated>
		<difficult>0</difficult>
		<bndbox>
			<xmin>398</xmin>
			<ymin>79</ymin>
			<xmax>410</xmax>
			<ymax>102</ymax>
		</bndbox>
	</object>
	<object>
		<name>ship</name>
		<pose>Unspecified</pose>
		<truncated>0</truncated>
		<difficult>0</difficult>
		<bndbox>
			<xmin>123</xmin>
			<ymin>174</ymin>
			<xmax>139</xmax>
			<ymax>230</ymax>
		</bndbox>
	</object>
</annotation>