<annotation>
	<folder>JPEGImages</folder>
	<filename>000187.jpg</filename>
	<path>JPEGImages</path>
	<size>
		<width>401</width>
		<height>315</height>
		<depth>3</depth>
	</size>
	<object>
		<name>ship</name>
		<pose>Unspecified</pose>
		<truncated>0</truncated>
		<difficult>0</difficult>
		<bndbox>
			<xmin>39</xmin>
			<ymin>23</ymin>
			<xmax>51</xmax>
			<ymax>49</ymax>
		</bndbox>
	</object>
	<object>
		<name>ship</name>
		<pose>Unspecified</pose>
		<truncated>0</truncated>
		<difficult>0</difficult>
		<bndbox>
			<xmin>126</xmin>
			<ymin>127</ymin>
			<xmax>139</xmax>
			<ymax>154</ymax>
		</bndbox>
	</object>
	<object>
		<name>ship</name>
		<pose>Unspecified</pose>
		<truncated>0</truncated>
		<difficult>0</difficult>
		<bndbox>
			<xmin>5</xmin>
			<ymin>254</ymin>
			<xmax>24</xmax>
			<ymax>300</ymax>
		</bndbox>
	</object>
</annotation>