<annotation>
	<folder>JPEGImages</folder>
	<filename>000376.jpg</filename>
	<path>JPEGImages</path>
	<size>
		<width>500</width>
		<height>386</height>
		<depth>3</depth>
	</size>
	<object>
		<name>ship</name>
		<pose>Unspecified</pose>
		<truncated>0</truncated>
		<difficult>0</difficult>
		<bndbox>
			<xmin>262</xmin>
			<ymin>52</ymin>
			<xmax>295</xmax>
			<ymax>85</ymax>
		</bndbox>
	</object>
	<object>
		<name>ship</name>
		<pose>Unspecified</pose>
		<truncated>0</truncated>
		<difficult>0</difficult>
		<bndbox>
			<xmin>94</xmin>
			<ymin>166</ymin>
			<xmax>107</xmax>
			<ymax>198</ymax>
		</bndbox>
	</object>
	<object>
		<name>ship</name>
		<pose>Unspecified</pose>
		<truncated>0</truncated>
		<difficult>0</difficult>
		<bndbox>
			<xmin>125</xmin>
			<ymin>269</ymin>
			<xmax>140</xmax>
			<ymax>300</ymax>
		</bndbox>
	</object>
</annotation>